comment/__init__.py
comment/admin.py
comment/apps.py
comment/forms.py
comment/managers.py
comment/mixins.py
comment/models.py
comment/settings.py
comment/tests.py
comment/urls.py
comment/views.py
comment/locale/fa/LC_MESSAGES/django.mo
comment/locale/fa/LC_MESSAGES/django.po
comment/migrations/0001_initial.py
comment/migrations/0002_config.py
comment/migrations/0003_comment_content_main_comment_status_edited_and_more.py
comment/migrations/__init__.py
comment/static/comment/css/comment.css
comment/static/comment/css/comment.min.css
comment/static/comment/font/Vazir/Vazirmatn-Black.woff2
comment/static/comment/font/Vazir/Vazirmatn-Bold.woff2
comment/static/comment/font/Vazir/Vazirmatn-ExtraBold.woff2
comment/static/comment/font/Vazir/Vazirmatn-ExtraLight.woff2
comment/static/comment/font/Vazir/Vazirmatn-Light.woff2
comment/static/comment/font/Vazir/Vazirmatn-Medium.woff2
comment/static/comment/font/Vazir/Vazirmatn-Regular.woff2
comment/static/comment/font/Vazir/Vazirmatn-SemiBold.woff2
comment/static/comment/font/Vazir/Vazirmatn-Thin.woff2
comment/static/comment/font/Vazir-FD/Vazirmatn-FD-Black.woff2
comment/static/comment/font/Vazir-FD/Vazirmatn-FD-Bold.woff2
comment/static/comment/font/Vazir-FD/Vazirmatn-FD-ExtraBold.woff2
comment/static/comment/font/Vazir-FD/Vazirmatn-FD-ExtraLight.woff2
comment/static/comment/font/Vazir-FD/Vazirmatn-FD-Light.woff2
comment/static/comment/font/Vazir-FD/Vazirmatn-FD-Medium.woff2
comment/static/comment/font/Vazir-FD/Vazirmatn-FD-Regular.woff2
comment/static/comment/font/Vazir-FD/Vazirmatn-FD-SemiBold.woff2
comment/static/comment/font/Vazir-FD/Vazirmatn-FD-Thin.woff2
comment/static/comment/img/profile.png
comment/static/comment/js/comment.js
comment/static/comment/js/comment.min.js
comment/static/comment/tailwindcss/style.css
comment/static/comment/tailwindcss/tailwind.config.js
comment/templates/comment/comment/comment_body.html
comment/templates/comment/comment/comment_counter.html
comment/templates/comment/comment/comment_list.html
django_comment_system-2.10.4.dist-info/LICENSE
django_comment_system-2.10.4.dist-info/METADATA
django_comment_system-2.10.4.dist-info/WHEEL
django_comment_system-2.10.4.dist-info/top_level.txt
django_comment_system-2.10.4.dist-info/RECORD
