Metadata-Version: 2.1
Name: django-comment-system
Version: 2.10.4
Summary: Django Comment System, It can be associated with any given model.
Home-page: https://github.com/mahyar-amiri/django-comment-system
Author: Mahyar Amiri
Author-email: mmaahhyyaarr@gmail.com
License: MIT
Project-URL: Documentation, https://github.com/mahyar-amiri/django-comment-system/README.md
Project-URL: Source Code, https://github.com/mahyar-amiri/django-comment-system
Keywords: django comment comment-system django-comment comments comments-system django-comments tailwind tailwindcss ajax
License-File: LICENSE
Requires-Dist: django
Requires-Dist: pillow
Requires-Dist: requests
Provides-Extra: markdown
Requires-Dist: markdown ; extra == 'markdown'
